llmterface_gemini/__init__.py
llmterface_gemini/chat.py
llmterface_gemini/config.py
llmterface_gemini/models.py
llmterface_gemini/plugin.py
llmterface_gemini-0.2.1.dist-info/METADATA
llmterface_gemini-0.2.1.dist-info/WHEEL
llmterface_gemini-0.2.1.dist-info/entry_points.txt
llmterface_gemini-0.2.1.dist-info/licenses/LICENSE
llmterface_gemini-0.2.1.dist-info/RECORD
