Metadata-Version: 2.4
Name: llmterface-gemini
Version: 0.2.1
Summary: Gemini provider for LLMterface
Author-email: "D. Zachary Wheeler" <celestialswashbuckler@gmail.com>
License-Expression: MIT
License-File: LICENSE
Keywords: ai,gemini,google,llm,plugin,provider
Requires-Python: <4.0,>=3.13
Requires-Dist: google-genai<2.0.0,>=1.25.0
Requires-Dist: llmterface<1.0.0,>=0.1.0
